{
  "lastUpdate": "2026-04-16 12:50:41",
  "data": [
    {
      "title": "nhl",
      "trafficCount": "200+",
      "pubDate": "Thu, 16 Apr 2026 05:30:00 -0700",
      "picture": "https://encrypted-tbn2.gstatic.com/images?q=tbn:ANd9GcRPkyQIZaysQKjk_SMROAP-kveHyectELITxkd4wSMqP_Y6XeXVKd1cAdclYq4",
      "pictureSource": "Sport.cz",
      "relatedSearch": [
        {
          "title": "NHL | Další bolest pro hvězdu NHL. S manželkou podruhé prožívají stejnou tragédii",
          "snippet": "",
          "url": "https://www.sport.cz/clanek/hokej-nhl-dalsi-bolest-pro-hvezdu-nhl-s-manzelkou-podruhe-prozivaji-stejnou-tragedii-5437458",
          "source": "Sport.cz"
        },
        {
          "title": "„Tohle mluví za vše.“ Česká hvězda je v NHL zpátky na dně",
          "snippet": "",
          "url": "https://sport.aktualne.cz/hokej/tohle-mluvi-za-vse-ceska-hvezda-je-v-nhl-zpatky-na-dne/r~aaa293a54e705b6fb9660a0a8a737897/",
          "source": "Aktuálně.cz - Víte, co se právě děje"
        },
        {
          "title": "Mladý fenomén mezi dospělými. Schaefer po životní sezoně vyhlíží zářnou budoucnost",
          "snippet": "",
          "url": "https://www.nhl.cz/mlady-fenomen-mezi-dospelymi-schaefer-po-zivotni-sezone-vyhlizi-zarnou-budoucnost/5035725",
          "source": "NHL.CZ"
        }
      ],
      "link": "https://imtaqin.id/"
    },
    {
      "title": "pbs",
      "trafficCount": "100+",
      "pubDate": "Thu, 16 Apr 2026 05:20:00 -0700",
      "picture": "https://encrypted-tbn3.gstatic.com/images?q=tbn:ANd9GcRSnGapCON7MRhRK43eB6-D6M7Bg8lXzOI01B6wQtcWX2rTS1dPxFrmeszCb2s",
      "pictureSource": "Chattanooga Pulse",
      "relatedSearch": [
        {
          "title": "WTCI PBS Brings “Be My Neighbor Day” Event To The Bessie Smith Cultural Center",
          "snippet": "",
          "url": "https://www.chattanoogapulse.com/citylife/news/pbs-brings-be-my-neighbor-day-event-to-the-bessie-smith-cu/",
          "source": "Chattanooga Pulse"
        },
        {
          "title": "April 18th is “Be My Neighbor Day” at Bessie Smith Cultural Center",
          "snippet": "",
          "url": "https://www.hits96.com/april-18th-is-be-my-neighbor-day-at-bessie-smith-cultural-center/",
          "source": "Hits 96"
        },
        {
          "title": "How Nine PBS is surviving, and even thriving, without federal funding",
          "snippet": "",
          "url": "https://www.stlmag.com/news/nine-pbs-amy-shaw-federal-funding/",
          "source": "St. Louis Magazine"
        }
      ],
      "link": "https://imtaqin.id/"
    },
    {
      "title": "opozice",
      "trafficCount": "200+",
      "pubDate": "Thu, 16 Apr 2026 04:20:00 -0700",
      "picture": "https://encrypted-tbn3.gstatic.com/images?q=tbn:ANd9GcRm47eBJ44VAlcQGBUcrU4OO4aqgL0303b7MTK8zPDz4Of0-jRtBbz2G8BHgbg",
      "pictureSource": "Seznam Zprávy",
      "relatedSearch": [
        {
          "title": "Čekal jsem od vás víc, vzkázal motorista Šťastný ODS kvůli mimořádné schůzi",
          "snippet": "",
          "url": "https://www.seznamzpravy.cz/clanek/domaci-politika-nejde-mlcet-a-prihlizet-opozice-svolala-mimoradnou-schuzi-kvuli-krokum-vlady-304164",
          "source": "Seznam Zprávy"
        },
        {
          "title": "Je to paskvil, míní Rakušan o návrhu změny financování veřejnoprávních médií",
          "snippet": "",
          "url": "https://ct24.ceskatelevize.cz/clanek/domaci/poslanci-budou-na-mimoradne-schuzi-resit-ceny-pohonnych-hmot-ci-verejnopravni-media-372432",
          "source": "ČT24"
        },
        {
          "title": "S vámi se nedá bavit, vyčetl Babiš opozici. Odmítl snahu ovládnout ČT",
          "snippet": "",
          "url": "https://www.idnes.cz/zpravy/domaci/snemovna-mimoradna-schuze-na-zadost-opozice.A260416_042105_domaci_kop",
          "source": "iDNES.cz"
        }
      ],
      "link": "https://imtaqin.id/"
    },
    {
      "title": "mikaela shiffrinová",
      "trafficCount": "500+",
      "pubDate": "Thu, 16 Apr 2026 03:40:00 -0700",
      "picture": "https://encrypted-tbn2.gstatic.com/images?q=tbn:ANd9GcSra6S9yIIQXsUkefOlGaZ4dfBJxBKFgpglcFB3JTjdlMElAaiYvlr-MXG-fSU",
      "pictureSource": "iDNES.cz",
      "relatedSearch": [
        {
          "title": "Shiffrinová se pochlubila novým kamarádem. Je jím krasobruslařská hvězda",
          "snippet": "",
          "url": "https://www.idnes.cz/sport/trendy/shiffrinova-se-pochlubila-novym-kamaradem-je-jim-krasobruslarska-hvezda.A260416_101017_trendy_subt",
          "source": "iDNES.cz"
        },
        {
          "title": "Shiffrinová na svahu s mladými lyžařkami. Pomáhá rozjet milionový projekt",
          "snippet": "",
          "url": "https://www.idnes.cz/sport/trendy/shiffrinova-na-svahu-s-mladymi-lyzarkami-pomaha-rozjet-milionovy-projekt.A260413_104657_trendy_subt",
          "source": "iDNES.cz"
        }
      ],
      "link": "https://imtaqin.id/"
    },
    {
      "title": "novinky.cz",
      "trafficCount": "200+",
      "pubDate": "Thu, 16 Apr 2026 03:20:00 -0700",
      "picture": "https://encrypted-tbn1.gstatic.com/images?q=tbn:ANd9GcSzKV1pX31cTNUAI3vydEdjQeL4APWqm0yMOsHPTw0Rrr9AIFM3TUzBPc8FYQI",
      "pictureSource": "Novinky",
      "relatedSearch": [
        {
          "title": "Trefa Miroslava Kalouska: Kdo chtěl všechno, nemá nic",
          "snippet": "",
          "url": "https://www.novinky.cz/clanek/komentare-trefa-miroslava-kalouska-kdo-chtel-vsechno-nema-nic-40573537",
          "source": "Novinky"
        },
        {
          "title": "Trefa Miroslava Kalouska: Kdo chtěl všechno, nemá nic",
          "snippet": "",
          "url": "https://www.stream.cz/komentare/trefa-miroslava-kalouska-kdo-chtel-vsechno-nema-nic-65491346",
          "source": "Stream.cz"
        },
        {
          "title": "Trefa Miroslava Kalouska: Kdo chtěl všechno, nemá nic",
          "snippet": "",
          "url": "https://www.prahanadlani.cz/clanek-zprava/1549286-trefa-miroslava-kalouska-kdo-chtel-vsechno-nema-nic.html",
          "source": "Prahanadlani.cz"
        }
      ],
      "link": "https://imtaqin.id/"
    },
    {
      "title": "aryna sabalenková",
      "trafficCount": "1000+",
      "pubDate": "Thu, 16 Apr 2026 02:20:00 -0700",
      "picture": "https://encrypted-tbn3.gstatic.com/images?q=tbn:ANd9GcQyZWVseQcY8YA_dRGbUSfk6XHXwmD-SsFu1twhohp1I4qdfk3lEP2LiGuzjfc",
      "pictureSource": "Sport.cz",
      "relatedSearch": [
        {
          "title": "Sabalenková při odvážném focení prozradila, co by dělala místo tenisu",
          "snippet": "",
          "url": "https://www.sport.cz/clanek/tenis-sabalenkova-pri-odvaznem-foceni-prozradila-co-by-delala-misto-tenisu-5437019",
          "source": "Sport.cz"
        },
        {
          "title": "Sabalenka vládne kurtům jako nikdo od roku 2022 a oslnila focením pro Esquire",
          "snippet": "",
          "url": "https://www.ruik.cz/sabalenka-vladne-kurtum-jako-nikdo-od-roku-2022-a-oslnila-focenim-pro-esquire/",
          "source": "Ruik"
        },
        {
          "title": "Sabalenková potřebuje ze sebe dostat agresi. Proto uvažuje o novém sportu",
          "snippet": "",
          "url": "https://www.nastartu.cz/sabalenkova-potrebuje-ze-sebe-dostat-agresi-proto-uvazuje-o-novem-sportu",
          "source": "Nastartu"
        }
      ],
      "link": "https://imtaqin.id/"
    },
    {
      "title": "rusko",
      "trafficCount": "2000+",
      "pubDate": "Thu, 16 Apr 2026 02:10:00 -0700",
      "picture": "https://encrypted-tbn3.gstatic.com/images?q=tbn:ANd9GcQoxJq2dixIeEOOxVYuB6TPcmZvh8fvKRQJuJV7rvegpnvv_n8d1mZLdclzeoI",
      "pictureSource": "Novinky",
      "relatedSearch": [
        {
          "title": "Rusové hrozí útokem na Česko kvůli podnikům, které vyrábějí drony pro Ukrajinu",
          "snippet": "",
          "url": "https://www.novinky.cz/clanek/zahranicni-evropa-rusove-hrozi-utokem-na-cesko-kvuli-podnikum-ktere-vyrabeji-drony-pro-ukrajinu-40573723",
          "source": "Novinky"
        },
        {
          "title": "Kyjev potřebuje dělostřelecké granáty, Moskva varuje Evropu kvůli dodávkám dronů",
          "snippet": "",
          "url": "https://www.seznamzpravy.cz/clanek/zahranicni-kyjev-potrebuje-delostrelecke-granaty-moskva-varuje-evropu-kvuli-dodavkam-dronu-304153",
          "source": "Seznam Zprávy"
        },
        {
          "title": "Ruskou hrozbu útokem na Česko řeší policie. Je to součást války, varuje firma",
          "snippet": "",
          "url": "https://tn.nova.cz/zpravodajstvi/clanek/645496-ruskou-hrozbu-utokem-na-cesko-resi-policie-je-to-soucast-valky-varuje-firma",
          "source": "TN.cz"
        }
      ],
      "link": "https://imtaqin.id/"
    },
    {
      "title": "adac",
      "trafficCount": "200+",
      "pubDate": "Thu, 16 Apr 2026 02:10:00 -0700",
      "picture": "https://encrypted-tbn0.gstatic.com/images?q=tbn:ANd9GcT1NU01q-isIihlZ81QMmofzlvn1_2Uzkxh7-HgZB6-Pnuxnjt4OSVrFeOWxOg",
      "pictureSource": "General-Anzeiger Bonn",
      "relatedSearch": [
        {
          "title": "24-Zoll-Räder: ADAC-Test: Viele Gute Kinder- und Jugendfahrräder - aber…",
          "snippet": "",
          "url": "https://ga.de/verkehr/news/adac-test-viele-gute-kinder-und-jugendfahrraeder-aber_aid-146913381",
          "source": "General-Anzeiger Bonn"
        },
        {
          "title": "Sicherer Start in den Straßenverkehr",
          "snippet": "",
          "url": "https://presse.adac.de/meldungen/adac-ev/tests/sicherer-start-in-den-strassenverkehr.html",
          "source": "ADAC Presse"
        },
        {
          "title": "„enjoy the ride“ live: woom Experience Days voller Inspiration, Bewegung und echter Fahrradliebe",
          "snippet": "",
          "url": "https://x-aces.com/familykids/2026/enjoy-the-ride-live-woom-experience-days-voller-inspiration-bewegung-und-echter-fahrradliebe/",
          "source": "X-ACES.com"
        }
      ],
      "link": "https://imtaqin.id/"
    },
    {
      "title": "summit nato",
      "trafficCount": "2000+",
      "pubDate": "Thu, 16 Apr 2026 02:00:00 -0700",
      "picture": "https://encrypted-tbn1.gstatic.com/images?q=tbn:ANd9GcRk6rayU9GzZp54I2HiaJOdy6-vMVR8-IRp2WA8ZrqxdzamO5xSQW5BT4nGMpk",
      "pictureSource": "Novinky",
      "relatedSearch": [
        {
          "title": "Babiš, Macinka, Zůna. Pavel na seznamu delegace na summit NATO chybí",
          "snippet": "",
          "url": "https://www.novinky.cz/clanek/domaci-babis-macinka-zuna-pavel-na-seznamu-delegace-na-summit-nato-chybi-40573656",
          "source": "Novinky"
        },
        {
          "title": "Dětinský způsob válčení, i prezident může vládě znepříjemňovat život, pohrozil Pavel",
          "snippet": "",
          "url": "https://www.idnes.cz/zpravy/domaci/petr-pavel-summit-nato-reflex-ucast-macinka-turek-babis-spor.A260416_102516_domaci_ikro",
          "source": "iDNES.cz"
        },
        {
          "title": "Vláda schválila cestu na summit NATO. S Pavlem v armádním letadle nepočítá",
          "snippet": "",
          "url": "https://www.seznamzpravy.cz/clanek/domaci-politika-na-summit-nato-poleti-babis-macinka-a-zuna-schvalila-vlada-304167",
          "source": "Seznam Zprávy"
        }
      ],
      "link": "https://imtaqin.id/"
    },
    {
      "title": "lucie borhyová",
      "trafficCount": "2000+",
      "pubDate": "Wed, 15 Apr 2026 23:50:00 -0700",
      "picture": "https://encrypted-tbn1.gstatic.com/images?q=tbn:ANd9GcShFic15nfPzTrajFxbq7956RKD7sjlATSpZePgWCNnkbYUZeD-i1S62iufSCI",
      "pictureSource": "Extra.cz",
      "relatedSearch": [
        {
          "title": "Utajený vztah Lucie Borhyové: Žije s úspěšným právníkem, tajemného fešáka skrývá před světem",
          "snippet": "",
          "url": "https://www.extra.cz/utajeny-vztah-lucie-borhyove-zije-s-uspesnym-pravnikem-tajemneho-fesaka-skryva-pred-svetem-b7a7c",
          "source": "Extra.cz"
        },
        {
          "title": "Třikrát zasnoubená, vdaná ani jednou. Lucie Borhyová měla na muže smůlu, po boku Smečky jenom září",
          "snippet": "",
          "url": "https://www.kafe.cz/celebrity/lucie-borhyova-vztahy/",
          "source": "Kafe.cz"
        },
        {
          "title": "Nejvnadnější česká moderátorka měla na muže smůlu a ani po trojích zásnubách k oltáři nedošla. Dnes slaví narozeniny",
          "snippet": "",
          "url": "https://www.svetzeny.cz/zabava/osobnosti/lucie-borhyova-48-let",
          "source": "SvětŽeny.cz"
        }
      ],
      "link": "https://imtaqin.id/"
    }
  ]
}