{
  "lastUpdate": "2026-05-25 10:44:36",
  "data": [
    {
      "title": "μετρο θεσσαλονικησ",
      "trafficCount": "100+",
      "pubDate": "Mon, 25 May 2026 03:30:00 -0700",
      "picture": "https://encrypted-tbn3.gstatic.com/images?q=tbn:ANd9GcQDtCnjd0jmZB_vBqmLc-H9Mvoy-0EnVEjT76m4xn0gMQkoVh9Pz749aGg-tkk",
      "pictureSource": "LiFO",
      "relatedSearch": [
        {
          "title": "Προβλήματα στο μετρό Θεσσαλονίκης: Συνωστισμός στους σταθμούς",
          "snippet": "",
          "url": "https://www.lifo.gr/now/greece/problima-sto-metro-thessalonikis-synostismos-stoys-stathmoys",
          "source": "LiFO"
        },
        {
          "title": "Μετρό Θεσσαλονίκης: Μετ΄εμποδίων τα δρομολόγια λόγω προβλήματος ηλεκτροδότησης - Πώς θα μετακινηθείτε",
          "snippet": "",
          "url": "https://www.reader.gr/ellada/metro-thessalonikis-metempodion-ta-dromologia-logo-problimatos-ilektrodotisis-pos-tha-metakinitheite/647636",
          "source": "Reader.gr"
        },
        {
          "title": "Μετρό Θεσσαλονίκης: Σε υποβαθμισμένη λειτουργία – Ποια είναι η αιτία",
          "snippet": "",
          "url": "https://parallaximag.gr/thessaloniki-news/metro-thessalonikis-se-ypovathmismeni-leitoyrgia-poia-einai-i-aitia",
          "source": "Parallaxi"
        }
      ],
      "link": "https://imtaqin.id/"
    },
    {
      "title": "μαΐου",
      "trafficCount": "1000+",
      "pubDate": "Mon, 25 May 2026 02:10:00 -0700",
      "picture": "https://encrypted-tbn1.gstatic.com/images?q=tbn:ANd9GcQUiBohzSw-DeC6_XkkBBty-tlXQI226yzFzEzP7j-cL8ABcuKkJXjTUzZ0EWQ",
      "pictureSource": "CNN.gr",
      "relatedSearch": [
        {
          "title": "Μπλε Σελήνη: Ποια ημέρα και ώρα θα δούμε τη δεύτερη πανσέληνο του Μαΐου",
          "snippet": "",
          "url": "https://www.cnn.gr/kosmos/story/534873/ble-selini-poia-imera-kai-ora-tha-doyme-ti-deyteri-panselino-tou-maiou",
          "source": "CNN.gr"
        },
        {
          "title": "Πανσέληνος στον Τοξότη: Η πιο αποκαλυπτική στιγμή του Μαΐου φέρνει στο φως αλήθειες που δεν μπορείς πια να αγνοήσεις",
          "snippet": "",
          "url": "https://www.tovima.gr/grace/good-life/panselinos-ston-toxoti-i-pio-apokalyptiki-stigmi-tou-maiou-fernei-sto-fos-alitheies-pou-den-boreis-pia-na-agnoiseis/",
          "source": "ΤΟ ΒΗΜΑ"
        },
        {
          "title": "Η δεύτερη Πανσέληνος του Μαΐου 2026: Πότε θα φωτίσει την πόλη το \"Μπλε Φεγγάρι\"",
          "snippet": "",
          "url": "https://www.athinorama.gr/plus/3072185/i-deuteri-panselinos-tou-maiou-2026-pote-tha-fotisei-to-mple-feggari/",
          "source": "Athinorama.gr"
        }
      ],
      "link": "https://imtaqin.id/"
    },
    {
      "title": "cretalive news",
      "trafficCount": "200+",
      "pubDate": "Mon, 25 May 2026 02:10:00 -0700",
      "picture": "https://encrypted-tbn0.gstatic.com/images?q=tbn:ANd9GcRp6zeogEg3m8N1NadGpaOCxHa8I0ShjyCpPm8KeGu0rJKpOP5dt6DCEmoOiFs",
      "pictureSource": "Kathimerini",
      "relatedSearch": [
        {
          "title": "ΟΠΕΚΕΠΕ: 20 νέες συλλήψεις στην Κρήτη – Πάνω από 2,5 εκατ. τα παράνομα κέρδη της οργάνωσης",
          "snippet": "",
          "url": "https://www.kathimerini.gr/society/564246187/opekepe-20-nees-syllipseis-stin-kriti-pano-apo-3-ekat-ta-paranoma-kerdi-tis-organosis/",
          "source": "Kathimerini"
        },
        {
          "title": "ΟΠΕΚΕΠΕ: Νέα αστυνομική επιχείρηση και 20 συλλήψεις στην Κρήτη - Πάνω από τρία εκατ. τα παράνομα κέρδη",
          "snippet": "",
          "url": "https://www.naftemporiki.gr/society/2114763/opekepe-nea-astynomiki-epicheirisi-kai-20-syllipseis-stin-kriti-pano-apo-tria-ekat-ta-paranoma-kerdi/",
          "source": "η ναυτεμπορικη"
        },
        {
          "title": "Αστυνομική επιχείρηση για παράνομες επιδοτήσεις ΟΠΕΚΕΠΕ στην Κρήτη – 20 συλλήψεις",
          "snippet": "",
          "url": "https://www.in.gr/2026/05/25/greece/astynomiki-epixeirisi-gia-paranomes-epidotiseis-opekepe-stin-kriti-20-syllipseis/",
          "source": "In.gr"
        }
      ],
      "link": "https://imtaqin.id/"
    },
    {
      "title": "η ναυτεμπορική",
      "trafficCount": "500+",
      "pubDate": "Mon, 25 May 2026 01:40:00 -0700",
      "picture": "",
      "pictureSource": "",
      "relatedSearch": [],
      "link": "https://imtaqin.id/"
    },
    {
      "title": "spanien",
      "trafficCount": "200+",
      "pubDate": "Mon, 25 May 2026 01:30:00 -0700",
      "picture": "https://encrypted-tbn3.gstatic.com/images?q=tbn:ANd9GcTIw4rMFwPZBB7uC3ObynFZbTinNI7r46gTzaqv9Vqm5xjOIs50T6ufAgh1J44",
      "pictureSource": "Watson.de",
      "relatedSearch": [
        {
          "title": "Schlechte Nachrichten für alle, die nach Spanien oder Griechenland reisen wollen",
          "snippet": "",
          "url": "https://www.watson.de/leben/318166672-schlechte-nachrichten-fuer-alle-die-nach-spanien-oder-griechenland-reisen-wollen",
          "source": "Watson.de"
        },
        {
          "title": "TUI AG-Aktie (DE000TUAG505): Quartalszahlen, Buchungstrends und neue Risiken im Blick",
          "snippet": "",
          "url": "https://www.ad-hoc-news.de/boerse/news/ueberblick/tui-ag-aktie-de000tuag505-quartalszahlen-buchungstrends-und-neue/69414947",
          "source": "AD HOC NEWS"
        },
        {
          "title": "Reiseanbieter aus Niedersachsen hofft auf Last-Minute-Sommer – diese Ziele stehen hoch im Kurs",
          "snippet": "",
          "url": "https://www.kreiszeitung.de/lokales/niedersachsen/reiseanbieter-aus-niedersachsen-hofft-auf-last-minute-sommer-diese-ziele-stehen-hoch-im-kurs-94309593.html",
          "source": "Kreiszeitung"
        }
      ],
      "link": "https://imtaqin.id/"
    },
    {
      "title": "airbus",
      "trafficCount": "100+",
      "pubDate": "Mon, 25 May 2026 01:20:00 -0700",
      "picture": "https://encrypted-tbn3.gstatic.com/images?q=tbn:ANd9GcSdNZGecwjM9gSs6hx4GmAYLdUNprhVuWzBBawWAX7yM86AuJ_Y8NjWqYn03qo",
      "pictureSource": "ارقام",
      "relatedSearch": [
        {
          "title": "Saudia receives first Airbus A321XLR in MEA",
          "snippet": "",
          "url": "https://www.argaam.com/en/article/articledetail/id/1908421",
          "source": "ارقام"
        },
        {
          "title": "Saudia’s First Airbus A321XLR Arrival in Jeddah and Riyadh to Trigger New Direct Flights to Madrid‑Barajas, Paris‑CDG, Milan‑Malpensa and Rome‑Fiumicino, Rival Emirates and Qatar Airways, Boost Tourism Demand from Spain, France, Italy and Maldives",
          "snippet": "",
          "url": "https://www.travelandtourworld.com/news/article/78ktfra87lm0/",
          "source": "Travel And Tour World"
        },
        {
          "title": "Saudia Takes Delivery Of First A321XLR With Biggest 24-Suite Business Cabin Yet",
          "snippet": "",
          "url": "https://simpleflying.com/saudia-first-airbus-a321xlr-delivery/",
          "source": "Simple Flying"
        }
      ],
      "link": "https://imtaqin.id/"
    },
    {
      "title": "αντζασ",
      "trafficCount": "20000+",
      "pubDate": "Mon, 25 May 2026 00:50:00 -0700",
      "picture": "https://encrypted-tbn3.gstatic.com/images?q=tbn:ANd9GcRRHB6kOb1IHrTeRCiOqmPrn5ZAY90Gupq1UDIu7f8VMvlM4nsbLa4DVCzIQic",
      "pictureSource": "ProtoThema",
      "relatedSearch": [
        {
          "title": "Θλίψη στο ελληνικό ποδόσφαιρο: Πέθανε ο Παρασκευάς Άντζας σε ηλικία 49 ετών, έπασχε από ALS",
          "snippet": "",
          "url": "https://www.protothema.gr/sports/article/1824230/pethane-o-paraskeuas-adzas-se-ilikia-49-eton/",
          "source": "ProtoThema"
        },
        {
          "title": "Πέθανε ο Παρασκευάς Άντζας σε ηλικία 49 ετών, σοκ στο ελληνικό ποδόσφαιρο",
          "snippet": "",
          "url": "https://www.newsit.gr/athlitika/pethane-o-paraskeyas-antzas-se-ilikia-49-eton-sok-sto-elliniko-podosfairo/4685237/",
          "source": "NewsIT"
        },
        {
          "title": "Πέθανε ο πρώην διεθνής ποδοσφαιριστής Παρασκευάς Άντζας σε ηλικία 49 ετών",
          "snippet": "",
          "url": "https://www.lifo.gr/now/sport/pethane-o-proin-diethnis-podosfairistis-paraskeyas-antzas-se-ilikia-49-eton",
          "source": "LiFO"
        }
      ],
      "link": "https://imtaqin.id/"
    },
    {
      "title": "εισιτήριο",
      "trafficCount": "2000+",
      "pubDate": "Mon, 25 May 2026 00:40:00 -0700",
      "picture": "https://encrypted-tbn3.gstatic.com/images?q=tbn:ANd9GcTKtcDrPxSvMBWqcZD2YZ3vWfztixT1vZX5hSqLApLb4LnkkY78Jn0dA7gQ53M",
      "pictureSource": "Gazzetta.gr",
      "relatedSearch": [
        {
          "title": "Final Four: Νέο πρόβλημα με τα εισιτήρια, oπαδοί του Ολυμπιακού δεν τα έχουν παραλάβει ακόμα",
          "snippet": "",
          "url": "https://www.gazzetta.gr/basketball/euroleague/2541843/final-four-neo-problima-me-ta-eisitiria-opadoi-toy-olympiakoy-den-ta",
          "source": "Gazzetta.gr"
        },
        {
          "title": "Τι ισχύει με όσους έχουν πρόβλημα με τα εισιτήριά τους: Τα ειδικά σημεία για φουλ εξυπηρέτηση από τη EuroLeague έξω από το T-Center",
          "snippet": "",
          "url": "https://www.sport24.gr/basket/ti-isxiei-me-osous-exoun-provlima-me-ta-eisitiria-tous-ta-eidika-simeia-gia-foul-exipiretisi-apo-ti-euroleague-exo-apo-to-t-center/",
          "source": "Sport24"
        },
        {
          "title": "Παρθενόπουλος: «Να φτάσουν το έβδομο, όπως ο Παναθηναϊκός» (video)",
          "snippet": "",
          "url": "https://www.novasports.gr/web-tv/sport/mpasket/event/euroleague/video/14906332/parthenopoulos-na-ftasoun-to-evdomo-opos-o-panathinaikos-video/",
          "source": "Novasports"
        }
      ],
      "link": "https://imtaqin.id/"
    },
    {
      "title": "πετρέλαιο",
      "trafficCount": "100+",
      "pubDate": "Mon, 25 May 2026 00:30:00 -0700",
      "picture": "https://encrypted-tbn3.gstatic.com/images?q=tbn:ANd9GcSnNkyctMUVV40IOF_1fybh73wWr1YaMGK1B4Q8GOT-7j-zQr5Lb-Tpq1AOOYE",
      "pictureSource": "η ναυτεμπορικη",
      "relatedSearch": [
        {
          "title": "Βυθίζεται το πετρέλαιο, πάρτι με νέα ρεκόρ στις αγορές - Πόσο γρήγορα θα ανοίξουν τα Στενά του Ορμούζ",
          "snippet": "",
          "url": "https://www.naftemporiki.gr/finance/markets/2114666/vythizetai-to-petrelaio-parti-me-nea-rekor-stis-agores-poso-grigora-tha-anoixoyn-ta-stena-toy-ormoyz/",
          "source": "η ναυτεμπορικη"
        },
        {
          "title": "Πετρέλαιο: Βουτιά 6% στις τιμές με την ελπίδα συμφωνίας ΗΠΑ - Ιράν",
          "snippet": "",
          "url": "https://www.capital.gr/agores/3994165/petrelaio-boutia-6-stis-times-me-tin-elpida-sumfonias-ipa-iran/",
          "source": "Capital.gr"
        },
        {
          "title": "Το πετρέλαιο καταρρέει, με πτώση που αγγίζει το 6%, καθώς «φουντώνουν» οι ελπίδες για συμφωνία ΗΠΑ με Ιράν",
          "snippet": "",
          "url": "https://www.newsit.gr/oikonomia/agores/to-petrelaio-katarreei-me-ptosi-pou-aggizei-to-6-kathos-fountonoun-oi-elpides-gia-symfonia-ipa-me-iran/4685063/",
          "source": "NewsIT"
        }
      ],
      "link": "https://imtaqin.id/"
    },
    {
      "title": "μάριο χεζόνια",
      "trafficCount": "1000+",
      "pubDate": "Mon, 25 May 2026 00:10:00 -0700",
      "picture": "https://encrypted-tbn0.gstatic.com/images?q=tbn:ANd9GcRRDA-mr_TokzlBbiyP75IbpXanqyeRez0V-_I_A1rtCeDTsg7MBFd6hR_Jx6s",
      "pictureSource": "Eurohoops",
      "relatedSearch": [
        {
          "title": "Χεζόνια: \"Έγιναν περίεργα πράγματα στο τέλος\"",
          "snippet": "",
          "url": "https://www.eurohoops.net/el/euroleague-el-2/1972336/chezonia-eginan-perierga-pragmata-sto-telos/",
          "source": "Eurohoops"
        },
        {
          "title": "Χεζόνια: «Δεν με ακουμπά το θέμα των οπαδών και το τι λέγεται απ' έξω - Δεν βλέπω τον αθλητισμό, ως... χούλιγκαν»",
          "snippet": "",
          "url": "https://www.skai.gr/news/sports/xezonia-den-me-akoumpa-to-thema-ton-opadon-kai-to-ti-legetai-ap-ekso",
          "source": "Skai.gr"
        },
        {
          "title": "Ο απόλυτος σεβασμός του Μάριο Χεζόνια προς το πρόσωπο του Γιώργου Μπαρτζώκα",
          "snippet": "",
          "url": "https://www.iefimerida.gr/spor/mario-hezonia-giorgos-mpartzokas-olympiakos-real",
          "source": "iefimerida.gr"
        }
      ],
      "link": "https://imtaqin.id/"
    }
  ]
}