{
  "lastUpdate": "2025-06-06 08:42:55",
  "data": [
    {
      "title": "mile kekin",
      "trafficCount": "100+",
      "pubDate": "Fri, 6 Jun 2025 00:10:00 -0700",
      "picture": "https://encrypted-tbn3.gstatic.com/images?q=tbn:ANd9GcQgSj-uC2H_LCq7fmbhmVk0ZUJ5AK8VwkMD-as57oTZxbAl7rP0zwIUzqdZXNU",
      "pictureSource": "Index.hr",
      "relatedSearch": [
        {
          "title": "Mile Kekin prekinuo šutnju intervjuom za Index. \"Od prosinca mi je najteže u životu\"",
          "snippet": "",
          "url": "https://www.index.hr/magazin/clanak/mile-kekin-prekinuo-sutnju-intervjuom-za-index-od-prosinca-mi-je-najteze-u-zivotu/2677156.aspx",
          "source": "Index.hr"
        },
        {
          "title": "Mile Kekin prvi put progovorio o uhićenju: 'Ujutro vodim psa u šetnju, prilaze mi muškarac i žena... Ostao sam preneražen'",
          "snippet": "",
          "url": "https://www.jutarnji.hr/vijesti/hrvatska/mile-kekin-prvi-put-progovorio-o-uhicenju-ujutro-vodim-psa-u-setnju-prilaze-mi-muskarac-i-zena-ostao-sam-prenerazen-15591178",
          "source": "Jutarnji list"
        },
        {
          "title": "Video. Mile Kekin opjevao vlastito hapšenje: 'Stavili mi lisice, kažu zbog kamera'",
          "snippet": "",
          "url": "https://www.telegram.hr/vijesti/video-mile-kekin-opjevao-vlastito-hapsenje-stavili-mi-lisice-kazu-zbog-kamera/",
          "source": "Telegram.hr"
        }
      ],
      "link": "https://imtaqin.id/"
    },
    {
      "title": "thunder vs pacers",
      "trafficCount": "100+",
      "pubDate": "Thu, 5 Jun 2025 22:20:00 -0700",
      "picture": "https://encrypted-tbn3.gstatic.com/images?q=tbn:ANd9GcRmgmCocpgVLjzYPIva8f1K-R7EmDU2Gd-JIS-W9EhCssivoxFqn8QB2eP9ed4",
      "pictureSource": "NBA",
      "relatedSearch": [
        {
          "title": "Cason Wallace starts Game 1 for Thunder, taking Isaiah Hartenstein's spot",
          "snippet": "",
          "url": "https://www.nba.com/news/nba-finals-thunder-insert-wallace-into-starting-lineup-game-1",
          "source": "NBA"
        },
        {
          "title": "Pacers 111-110 Thunder (Jun 5, 2025) Final Score",
          "snippet": "",
          "url": "https://www.espn.com/nba/game/_/gameId/401766122/pacers-thunder",
          "source": "ESPN"
        },
        {
          "title": "How to Watch the 2025 NBA Finals Online Without Cable for Free",
          "snippet": "",
          "url": "https://variety.com/2025/shopping/news/how-to-watch-nba-finals-online-livestream-free-1236417925/",
          "source": "Variety"
        }
      ],
      "link": "https://imtaqin.id/"
    },
    {
      "title": "čile – argentina",
      "trafficCount": "200+",
      "pubDate": "Thu, 5 Jun 2025 21:40:00 -0700",
      "picture": "https://encrypted-tbn2.gstatic.com/images?q=tbn:ANd9GcSTA1SWq5HRksT1thef7EI_0vDAAY7lAjUkzBBmRqncX_3tom3TyEdlOE3EzQE",
      "pictureSource": "Sportske novosti",
      "relatedSearch": [
        {
          "title": "Agonija na startu za Ancelottija i Brazil: ‘Ovo je sjena nekad velike momčadi, nema šećera...‘",
          "snippet": "",
          "url": "https://sportske.jutarnji.hr/sn/nogomet/nogomet-medjunarodni/agonija-na-startu-za-ancelottija-i-brazil-ovo-je-sjena-nekad-velike-momcadi-nema-secera-15591749",
          "source": "Sportske novosti"
        },
        {
          "title": "Carlo Ancelotti ostao bez pobjede u debiju na klupi Brazila",
          "snippet": "",
          "url": "https://www.tportal.hr/sport/clanak/carlo-ancelotti-ostao-bez-pobjede-u-debiju-na-klupi-brazila-20250606",
          "source": "tportal.hr"
        },
        {
          "title": "Ancelotti nakon kiksa u debiju s Brazilom: Ne izvlačim se, ali teren je bio loš",
          "snippet": "",
          "url": "https://www.index.hr/sport/clanak/ancelotti-nakon-kiksa-u-debiju-s-brazilom-ne-izvlacim-se-ali-teren-je-bio-los/2678041.aspx",
          "source": "Index.hr"
        }
      ],
      "link": "https://imtaqin.id/"
    },
    {
      "title": "ekvador – brazil",
      "trafficCount": "200+",
      "pubDate": "Thu, 5 Jun 2025 20:40:00 -0700",
      "picture": "https://encrypted-tbn2.gstatic.com/images?q=tbn:ANd9GcTNpROENxssYromLIw3JMHT1oqSaIrc0c3LAV0Z4yjIk_M_ikSKPe0LGBXWuak",
      "pictureSource": "ESPN India",
      "relatedSearch": [
        {
          "title": "Neymar out of Ancelotti's first Brazil squad",
          "snippet": "",
          "url": "https://www.espn.in/football/story/_/id/45333349/neymar-left-carlo-ancelotti-first-brazil-squad",
          "source": "ESPN India"
        },
        {
          "title": "What Carlo Ancelotti told Matheus Cunha and Brazil squad after ‘struggled’ draw vs Ecuador",
          "snippet": "",
          "url": "https://utddistrict.co.uk/what-carlo-ancelotti-told-matheus-cunha-and-brazil-squad-after-struggled-draw-v-ecuador/06/06/2025/",
          "source": "utddistrict.co.uk"
        },
        {
          "title": "Bruno Guimaraes suffers Guayaquil setback",
          "snippet": "",
          "url": "https://onefootball.com/en/news/bruno-guimaraes-suffers-guayaquil-setback-41211205",
          "source": "OneFootball"
        }
      ],
      "link": "https://imtaqin.id/"
    },
    {
      "title": "nba",
      "trafficCount": "200+",
      "pubDate": "Thu, 5 Jun 2025 18:10:00 -0700",
      "picture": "https://encrypted-tbn2.gstatic.com/images?q=tbn:ANd9GcTY7guaLVuV-vZ7OTvLETLx63M8TxhWg8FeOckslqDXBg0xu-mLkSOJxD1fz4Y",
      "pictureSource": "AP News",
      "relatedSearch": [
        {
          "title": "NBA Finals: Haliburton caps huge rally with winning jumper as Pacers stun Thunder 111-110 in Game 1",
          "snippet": "",
          "url": "https://apnews.com/article/nba-finals-2025-thunder-pacers-8966a303b1059b4e11b3b178dcea0567",
          "source": "AP News"
        },
        {
          "title": "Cameras caught Tyrese Haliburton's dad's smug reaction to Game 1 buzzer-beater",
          "snippet": "",
          "url": "https://ftw.usatoday.com/story/sports/nba/2025/06/05/tyrese-haliburton-dad-smug-reaction-pacers-buzzer-beater-nba-finals-game-1/84062544007/",
          "source": "USA Today"
        },
        {
          "title": "Clutch Hali AGAIN! Game 1 takeaways + KD rumors with Tom Haberstroh & NBA Draft talk with the Barlowes | The Kevin O'Connor Show",
          "snippet": "",
          "url": "https://sports.yahoo.com/nba/article/clutch-hali-again-game-1-takeaways--kd-rumors-with-tom-haberstroh--nba-draft-talk-with-the-barlowes--the-kevin-oconnor-show-045933166.html",
          "source": "Yahoo Sports"
        }
      ],
      "link": "https://imtaqin.id/"
    },
    {
      "title": "bajram",
      "trafficCount": "2000+",
      "pubDate": "Thu, 5 Jun 2025 15:50:00 -0700",
      "picture": "https://encrypted-tbn2.gstatic.com/images?q=tbn:ANd9GcTrGy-UoYU3SqLx14j4JM5Gl8wPCeqlXRruj6RFy-flUKmaqVgkHhK5VOWOX_E",
      "pictureSource": "Index.hr",
      "relatedSearch": [
        {
          "title": "Plenković čestitao Kurban-bajram",
          "snippet": "",
          "url": "https://www.index.hr/vijesti/clanak/plenkovic-cestitao-kurbanbajram/2678019.aspx",
          "source": "Index.hr"
        },
        {
          "title": "Kako žive splitski muslimani? Uoči Bajrama posjetili smo imama i njegovu Suadu: 'Imamo dobre susjede, dođu i časne...'",
          "snippet": "",
          "url": "https://slobodnadalmacija.hr/mozaik/zivot/kako-zive-splitski-muslimani-uoci-bajrama-posjetili-smo-imama-i-njegovu-suadu-imamo-dobre-susjede-dodu-i-casne-1480921",
          "source": "Slobodna Dalmacija"
        },
        {
          "title": "Šuta čestitao Kurban-bajram: 'Neka vas poruka solidarnosti vodi svaki dan'",
          "snippet": "",
          "url": "https://dalmatinskiportal.hr/vijesti/suta-cestitao-kurban-bajram-neka-vas-poruka-solidarnosti-vodi-svaki-dan-/238893",
          "source": "Dalmatinski portal"
        }
      ],
      "link": "https://imtaqin.id/"
    },
    {
      "title": "ginny and georgia",
      "trafficCount": "200+",
      "pubDate": "Thu, 5 Jun 2025 15:00:00 -0700",
      "picture": "https://encrypted-tbn3.gstatic.com/images?q=tbn:ANd9GcQUxF3qFWvzqETEwoUy3QNxIFUYH2gW0piteK_lDVKQoB2jbIEL3TtBUpsQ8TE",
      "pictureSource": "Cosmopolitan",
      "relatedSearch": [
        {
          "title": "How old are the Ginny and Georgia cast? The characters vs the actors who play them",
          "snippet": "",
          "url": "https://www.cosmopolitan.com/uk/entertainment/g64965872/ginny-and-georgia-cast-characters-ages/",
          "source": "Cosmopolitan"
        },
        {
          "title": "Ginny & Georgia Season 3 Ending Explained: Does Georgia Go to Jail?",
          "snippet": "",
          "url": "https://www.netflix.com/tudum/articles/ginny-and-georgia-season-3-ending-explained",
          "source": "Netflix"
        },
        {
          "title": "Now's The Time For Gilmore Girls Fans To Check Out This ‘Addictive’ Netflix Series If You Haven't Already",
          "snippet": "",
          "url": "https://ca.news.yahoo.com/nows-time-gilmore-girls-fans-060935952.html",
          "source": "Yahoo News Canada"
        }
      ],
      "link": "https://imtaqin.id/"
    },
    {
      "title": "sisak",
      "trafficCount": "100+",
      "pubDate": "Thu, 5 Jun 2025 13:50:00 -0700",
      "picture": "https://encrypted-tbn0.gstatic.com/images?q=tbn:ANd9GcR517ArUNhOlWtkbf7nkfrHAAEIJxuVmjv5NtCE-dJQT39Lwz726tRRgGxxouU",
      "pictureSource": "24sata.hr",
      "relatedSearch": [
        {
          "title": "Ovih 12 gore je od potresa: Dižu si plaće, daju poslove sinovima, parazitiraju na javnom novcu...",
          "snippet": "",
          "url": "https://www.24sata.hr/news/ovih-12-gore-je-od-potresa-dizu-si-place-daju-poslove-sinovima-parazitiraju-na-javnom-novcu-1055958",
          "source": "24sata.hr"
        },
        {
          "title": "Manipulativne tvrdnje novog gradonačelnika Siska koji si je u startu značajno povećao plaću",
          "snippet": "",
          "url": "https://faktograf.hr/2025/06/05/manipulativne-tvrdnje-novog-gradonacelnika-siska-koji-si-je-u-startu-znacajno-povecao-placu/",
          "source": "Faktograf.hr"
        },
        {
          "title": "Jučer tvrdio jedno, danas veliki obrat: Umjesto 4300 eura, sada će mu plaća biti ovolika",
          "snippet": "",
          "url": "https://net.hr/danas/rtl-danas/od-najvise-do-najnize-javni-pritisak-natjerao-gradonacelnika-siska-na-povlacenje-93cee065-4231-11f0-be08-9600040c8f8e",
          "source": "Net.hr"
        }
      ],
      "link": "https://imtaqin.id/"
    },
    {
      "title": "cherki",
      "trafficCount": "200+",
      "pubDate": "Thu, 5 Jun 2025 13:40:00 -0700",
      "picture": "https://encrypted-tbn2.gstatic.com/images?q=tbn:ANd9GcQdAKZ9qna84N3eH9tXcuqRC9CZBodBsBiuTPWbqed5eTOtG2SgPoaOkF0pIQo",
      "pictureSource": "L'Équipe",
      "relatedSearch": [
        {
          "title": "Rayan Cherki a affronté l'Espagne en Ligue des nations... sans ses crampons habituels",
          "snippet": "",
          "url": "https://www.lequipe.fr/Football/Actualites/Rayan-cherki-a-affronte-l-espagne-en-ligue-des-nations-sans-ses-crampons-habituels/1568042",
          "source": "L'Équipe"
        },
        {
          "title": "OL : Cherki (France), Diarra (Mali), Almada et Tagliafico (Argentine) sur les terrains ce jeudi",
          "snippet": "",
          "url": "https://www.olympique-et-lyonnais.com/ol-cherki-france-diarra-mali-almada-et-tagliafico-argentine-sur-les-terrains-ce-jeudi,364129.html",
          "source": "Olympique & Lyonnais"
        },
        {
          "title": "Équipe de France - Lucas Hernandez est totalement fan de Rayan Cherki !",
          "snippet": "",
          "url": "https://madeinparisiens.ouest-france.fr/infos/article-equipe-de-france-lucas-hernandez-est-totalement-fan-de-rayan-cherki-485051.html",
          "source": "MadeInParisiens"
        }
      ],
      "link": "https://imtaqin.id/"
    },
    {
      "title": "huijsen",
      "trafficCount": "200+",
      "pubDate": "Thu, 5 Jun 2025 13:30:00 -0700",
      "picture": "https://encrypted-tbn1.gstatic.com/images?q=tbn:ANd9GcSVftU3Zw_k391_31cjWW19E-lEZV99qq-r2pR-590WRXj9ezrYy_r-nLlo3Ho",
      "pictureSource": "Yahoo Sports",
      "relatedSearch": [
        {
          "title": "De la Fuente on Dean Huijsen: 'This is why he was signed by Real Madrid'",
          "snippet": "",
          "url": "https://sports.yahoo.com/video/la-fuente-dean-huijsen-why-063922765.html",
          "source": "Yahoo Sports"
        },
        {
          "title": "Spain coach praises Dean Huijsen after 5-4 win against France",
          "snippet": "",
          "url": "https://www.managingmadrid.com/2025/6/6/24444201/huijsen-spain-praise-2025-news-quotes",
          "source": "Managing Madrid"
        },
        {
          "title": "Official: Real Madrid new signing starts for Spain against France",
          "snippet": "",
          "url": "https://madriduniversal.com/official-real-madrid-new-signing-starts-for-spain-against-france/",
          "source": "Madrid Universal"
        }
      ],
      "link": "https://imtaqin.id/"
    }
  ]
}