{
  "lastUpdate": "2025-09-20 12:25:44",
  "data": [
    {
      "title": "real madrid vs espanyol timeline",
      "trafficCount": "200+",
      "pubDate": "Sat, 20 Sep 2025 04:50:00 -0700",
      "picture": "https://encrypted-tbn1.gstatic.com/images?q=tbn:ANd9GcQcJQietAPVcJG66BZku84Ckpty5g6M6MARVOb1pAxS-8Er3spP_o5547OxyDM",
      "pictureSource": "Sports Illustrated",
      "relatedSearch": [
        {
          "title": "Real Madrid vs. Espanyol: Preview, Predictions and Lineups",
          "snippet": "",
          "url": "https://www.si.com/soccer/real-madrid-vs-espanyol-preview-predictions-lineups-la-liga-9-20-25",
          "source": "Sports Illustrated"
        },
        {
          "title": "Vinicius, Brahim start in a 4-3-3 – How Real Madrid can line up against Espanyol",
          "snippet": "",
          "url": "https://sports.yahoo.com/article/vinicius-brahim-start-4-3-091000255.html",
          "source": "Yahoo Sports"
        },
        {
          "title": "Real Madrid vs. Espanyol live stream: Where to watch LaLiga online, odds, Vinicius Jr. expected to start",
          "snippet": "",
          "url": "https://www.cbssports.com/soccer/news/real-madrid-vs-espanyol-live-stream-where-to-watch-laliga-online-odds-vinicius-jr-expected-to-start/",
          "source": "CBS Sports"
        }
      ],
      "link": "https://imtaqin.id/"
    },
    {
      "title": "liverpool vs everton",
      "trafficCount": "100+",
      "pubDate": "Sat, 20 Sep 2025 04:50:00 -0700",
      "picture": "https://encrypted-tbn1.gstatic.com/images?q=tbn:ANd9GcRGkhC6QVhP8IoL4ceLmhCwlANeN_D0Nd0ffwPKpRbMvSYxaiK5Wut0trqksNc",
      "pictureSource": "Gazeta Express",
      "relatedSearch": [
        {
          "title": "Fears over Merseyside derby postponement after Met Office weather warning",
          "snippet": "",
          "url": "https://www.gazetaexpress.com/en/Fears-over-Merseyside-derby-postponement-after-Met-Office-weather-warning/",
          "source": "Gazeta Express"
        },
        {
          "title": "Football Tracker: Liverpool taking on Everton, Bayern and Real in action soon",
          "snippet": "",
          "url": "https://www.flashscore.com/news/football-tracker-live-scores-and-updates/2c8K7HoS/",
          "source": "Flashscore.com"
        },
        {
          "title": "Alexander Isak & Florian Wirtz DROPPED for Merseyside derby as Arne Slot shuffles pack ahead of crucial Premier League clash",
          "snippet": "",
          "url": "https://www.goal.com/en/lists/alexander-isak-florian-wirtz-dropped-merseyside-derby-arne-slot-shuffles-pack-crucial-premier-league/blt3c5ca8b87b20aa8a",
          "source": "Goal.com"
        }
      ],
      "link": "https://imtaqin.id/"
    }
  ]
}