{
  "lastUpdate": "2026-02-07 20:29:40",
  "data": [
    {
      "title": "nantes - lyon",
      "trafficCount": "200+",
      "pubDate": "Sat, 7 Feb 2026 12:00:00 -0800",
      "picture": "https://encrypted-tbn3.gstatic.com/images?q=tbn:ANd9GcTX7MxfGdP0LonVo1siKfTLZU024QGCd8F6KdYyG_QD9oxsoK-JKE1tXaVOdE8",
      "pictureSource": "Olympique & Lyonnais",
      "relatedSearch": [
        {
          "title": "Nantes - OL : Noah Nartey préféré à Khalis Merah",
          "snippet": "",
          "url": "https://www.olympique-et-lyonnais.com/nantes-ol-noah-nartey-prefere-a-khalis-merah,390265.html",
          "source": "Olympique & Lyonnais"
        },
        {
          "title": "Olympique Lyonnais - H-2 avant le coup d'envoi (21h05)",
          "snippet": "",
          "url": "https://www.fcnantes.com/articles/article2809.php?num=48608",
          "source": "FC Nantes"
        },
        {
          "title": "Pronostic Nantes – Lyon | Ligue 1 – 7 février 2026",
          "snippet": "",
          "url": "https://www.kelbet.com/pronostic-nantes-lyon-ligue-1-7-fevrier-2026/",
          "source": "Kelbet"
        }
      ],
      "link": "https://imtaqin.id/"
    },
    {
      "title": "jack nicholson",
      "trafficCount": "100+",
      "pubDate": "Sat, 7 Feb 2026 12:00:00 -0800",
      "picture": "https://encrypted-tbn1.gstatic.com/images?q=tbn:ANd9GcTV-0YmqKHbEH9RY3oJ5XUXQ7aBf5m4EBrclY9tknzyZIG7rjoeJsYeBwuTYdE",
      "pictureSource": "People.com",
      "relatedSearch": [
        {
          "title": "Michael Douglas Says Jack Nicholson Used to Tease Him For This One Very Specific Thing",
          "snippet": "",
          "url": "https://people.com/michael-douglas-says-jack-nicholson-used-to-tease-him-for-this-one-thing-11901673",
          "source": "People.com"
        },
        {
          "title": "Heartburn (1986 film)",
          "snippet": "",
          "url": "https://www.mailplus.co.uk/tv/finder/film/443460/heartburn-1986-film",
          "source": "Mail Plus"
        },
        {
          "title": "‘Highly underrated’ comedy starring two Oscar winners streaming now on Netflix",
          "snippet": "",
          "url": "https://www.express.co.uk/entertainment/films/2167799/highly-underrated-comedy-starring-two",
          "source": "Daily Express"
        }
      ],
      "link": "https://imtaqin.id/"
    },
    {
      "title": "real sociedad - elche",
      "trafficCount": "1000+",
      "pubDate": "Sat, 7 Feb 2026 11:20:00 -0800",
      "picture": "https://encrypted-tbn2.gstatic.com/images?q=tbn:ANd9GcSPy_9LWO_R4wE_CHWuSqAAJ5zk01f00GkOUJcS9XgDRJP7-g8J2DgJAmdJpes",
      "pictureSource": "365Scores",
      "relatedSearch": [
        {
          "title": "Qué canal pasa Real Sociedad vs Elche hoy: dónde ver gratis y EN VIVO LaLiga",
          "snippet": "",
          "url": "https://www.365scores.com/es/news/real-sociedad-vs-elche-donde-ver-canal/",
          "source": "365Scores"
        },
        {
          "title": "Matarazzo rota pensando en la Copa y Sarabia sorprende con Neto",
          "snippet": "",
          "url": "https://www.infobae.com/espana/agencias/2026/02/07/matarazzo-rota-pensando-en-la-copa-y-sarabia-sorprende-con-neto/",
          "source": "Infobae"
        },
        {
          "title": "Real Sociedad - Elche, en directo La Liga: resultado, goleadores y estadísticas en vivo",
          "snippet": "",
          "url": "https://www.elespanol.com/deportes/20260207/real-sociedad-elche-directo-liga-resultado-goleadores-estadisticas-vivo/1003744120878_22.html",
          "source": "El Español"
        }
      ],
      "link": "https://imtaqin.id/"
    },
    {
      "title": "ilia malinin",
      "trafficCount": "500+",
      "pubDate": "Sat, 7 Feb 2026 11:20:00 -0800",
      "picture": "https://encrypted-tbn0.gstatic.com/images?q=tbn:ANd9GcSikCFmQ6MJ-fqdSG-bDpEUChuAv6rwnk1Jxx63TigGetvigZptMTSrCLuQPnU",
      "pictureSource": "Milano Cortina 2026",
      "relatedSearch": [
        {
          "title": "Winter Olympics 2026: Ilia Malinin makes Olympic debut with solid short program, sits second",
          "snippet": "",
          "url": "https://www.olympics.com/en/milano-cortina-2026/news/winter-olympics-2026-ilia-malinin-makes-olympic-debut-with-solid-short-program",
          "source": "Milano Cortina 2026"
        },
        {
          "title": "Are backflips allowed in figure skating? What to know",
          "snippet": "",
          "url": "https://www.usatoday.com/story/sports/olympics/2026/02/07/are-backflips-allowed-in-figure-skating/88567458007/",
          "source": "USA Today"
        },
        {
          "title": "The Crazy Jumps That Make This American the World’s Best Figure Skater",
          "snippet": "",
          "url": "https://www.wsj.com/sports/olympics/ilia-malinin-quad-god-figure-skating-669549df",
          "source": "The Wall Street Journal"
        }
      ],
      "link": "https://imtaqin.id/"
    },
    {
      "title": "fiorentina - torino",
      "trafficCount": "1000+",
      "pubDate": "Sat, 7 Feb 2026 11:10:00 -0800",
      "picture": "https://encrypted-tbn0.gstatic.com/images?q=tbn:ANd9GcT9KgF3I0-oJZYNUijpPPbfP0jT11iyv90MK9X_wyjhOZhe55gIJ7BNTE9FgQM",
      "pictureSource": "La Gazzetta dello Sport",
      "relatedSearch": [
        {
          "title": "LIVE Fiorentina-Torino 0-1: gol di Casadei. Comuzzo di testa va vicino al pareggio",
          "snippet": "",
          "url": "https://www.gazzetta.it/Calcio/Serie-A/Fiorentina/07-02-2026/fiorentina-torino-live-diretta-serie-a.shtml",
          "source": "La Gazzetta dello Sport"
        },
        {
          "title": "Bucchioni: \"Non mi preoccupa l'assenza di Gosens, importante il ritorno di Kean anche se non segna\"",
          "snippet": "",
          "url": "https://www.labaroviola.com/bucchioni-non-mi-preoccupa-lassenza-di-gosens-importante-il-ritorno-di-kean-anche-se-non-segna/338468/",
          "source": "Labaro Viola"
        },
        {
          "title": "Fiorentina-Torino, le formazioni ufficiali",
          "snippet": "",
          "url": "https://www.torinofc.it/news/07/02/2026/fiorentina-torino-le-formazioni-ufficiali_41092",
          "source": "TORINO FC 1906"
        }
      ],
      "link": "https://imtaqin.id/"
    },
    {
      "title": "gerard butler",
      "trafficCount": "200+",
      "pubDate": "Sat, 7 Feb 2026 10:50:00 -0800",
      "picture": "https://encrypted-tbn1.gstatic.com/images?q=tbn:ANd9GcTejpNWXEfswujK3Kuk3C7Eqy78_PBs8SD_FAgbEbHsgyIX1avoHVbC7PImODY",
      "pictureSource": "Deadline",
      "relatedSearch": [
        {
          "title": "‘Empire City’: First Look At Gerard Butler In Action-Thriller With Hayley Atwell, Omari Hardwick",
          "snippet": "",
          "url": "https://deadline.com/2026/02/gerard-butler-empire-city-first-look-omari-hardwick-1236711064/",
          "source": "Deadline"
        },
        {
          "title": "Gerard Butler is on a rescue mission in a first-look image for the upcoming action thriller Empire City",
          "snippet": "",
          "url": "https://www.joblo.com/empire-city-gerard-butler/",
          "source": "JoBlo"
        },
        {
          "title": "Gerard Butler Is a Tough Navy SEAL-Turned-Firefighter in First Look at Action Thriller 'Empire City'",
          "snippet": "",
          "url": "https://movieweb.com/empire-city-gerard-butler-first-look-action-thriller/",
          "source": "MovieWeb"
        }
      ],
      "link": "https://imtaqin.id/"
    },
    {
      "title": "cav survivor",
      "trafficCount": "200+",
      "pubDate": "Sat, 7 Feb 2026 10:50:00 -0800",
      "picture": "https://encrypted-tbn2.gstatic.com/images?q=tbn:ANd9GcQoxaXCD0PFjUJwxD-jWBQj6Mp-L2HC-e73CN4RMzxz_KfHHxfedQqqVwS-oyw",
      "pictureSource": "Libertatea",
      "relatedSearch": [
        {
          "title": "Cine este CAV, concurent la Survivor România 2026. Are 5 copii și e pasionat de psihologie",
          "snippet": "",
          "url": "https://www.libertatea.ro/entertainment/cine-este-cav-concurent-la-survivor-romania-2026-are-5-copii-si-e-pasionat-de-psihologie-5616660",
          "source": "Libertatea"
        },
        {
          "title": "Cine este CAV, noul concurent de la Survivor România 2026. El intră în echipa Războinicilor",
          "snippet": "",
          "url": "https://a1.ro/survivor/stiri/cine-este-cav-noul-concurent-de-la-survivor-romania-2026-el-intra-in-echipa-razboinicilor-id1151322.html",
          "source": "A1.RO"
        }
      ],
      "link": "https://imtaqin.id/"
    },
    {
      "title": "marian godina",
      "trafficCount": "500+",
      "pubDate": "Sat, 7 Feb 2026 10:10:00 -0800",
      "picture": "https://encrypted-tbn3.gstatic.com/images?q=tbn:ANd9GcSptC52fo6ZYQx23fGKa7smOHHrOgNc-R86Z_NxGb-rdhjLFYdQ4UwfbRwy1LY",
      "pictureSource": "Libertatea",
      "relatedSearch": [
        {
          "title": "Marian Godină, replici sarcastice la adresa lui Cristian Boureanu și Călin Donca la Survivor România 2026",
          "snippet": "",
          "url": "https://www.libertatea.ro/entertainment/marian-godina-replici-sarcastice-la-adresa-lui-cristian-boureanu-si-calin-donca-la-survivor-romania-2026-5616425",
          "source": "Libertatea"
        },
        {
          "title": "„Un șarlatan mincinos!”. De ce îl urăște Godină pe Donca, de fapt. Cei doi tocmai…",
          "snippet": "",
          "url": "https://www.gandul.ro/actualitate/un-sarlatan-mincinos-de-ce-are-il-uraste-godina-pe-donca-de-fapt-cei-doi-tocmai-au-devenit-colegi-la-survivor-20796604",
          "source": "Gândul"
        },
        {
          "title": "Survivor România, 7 februarie 2026. Prima noapte pentru Marian Godină și Andreea Munteanu în tabăra Faimoșilor",
          "snippet": "",
          "url": "https://a1.ro/survivor/video/survivor-romania-7-februarie-2026-prima-noapte-pentru-marian-godina-si-andreea-munteanu-in-tabara-faimosilor-id1151370.html",
          "source": "A1.RO"
        }
      ],
      "link": "https://imtaqin.id/"
    },
    {
      "title": "automobil electric",
      "trafficCount": "500+",
      "pubDate": "Sat, 7 Feb 2026 10:10:00 -0800",
      "picture": "https://encrypted-tbn3.gstatic.com/images?q=tbn:ANd9GcTIylToQQUQCkX8oOpyfLiD2xEeEcn-Key9FmYZ9dBbG5I_T9XlV622hYtGo50",
      "pictureSource": "The New York Times",
      "relatedSearch": [
        {
          "title": "Carney Stakes Canada’s Auto Future on E.V.s as It Pulls Away From the U.S.",
          "snippet": "",
          "url": "https://www.nytimes.com/2026/02/05/world/canada/carney-canada-electric-vehicles-trump-trade.html",
          "source": "The New York Times"
        },
        {
          "title": "Will Canada's new auto strategy put as many EVs on the road as Carney says?",
          "snippet": "",
          "url": "https://www.cbc.ca/news/politics/electric-vehicles-climate-change-mark-carney-9.7078401",
          "source": "CBC"
        },
        {
          "title": "Canada to Toughen Tailpipe Emissions Standards",
          "snippet": "",
          "url": "https://www.wsj.com/business/autos/canada-to-toughen-tailpipe-emissions-standards-9c452682?gaa_at=eafs&gaa_n=AWEtsqdfzI7hXanH3L7dM38vVjf5fCOu33iYU5IutNWFUK_SFKWtxuHZMnfJ&gaa_ts=6987a438&gaa_sig=fz3ZJioUjomrK1a0F_GbssXsw0Zv5UAbbqk5pYPPKZAi1yxIHext-4KvEpOi8DTtEHwBFaLll4zwHcfcLmfI0A%3D%3D",
          "source": "The Wall Street Journal"
        }
      ],
      "link": "https://imtaqin.id/"
    },
    {
      "title": "daniela toth",
      "trafficCount": "500+",
      "pubDate": "Sat, 7 Feb 2026 10:00:00 -0800",
      "picture": "https://encrypted-tbn3.gstatic.com/images?q=tbn:ANd9GcQ89_lq2Z4VORF6QWovYLMX3jPSRO6Ox0YKcF6ziJK-r-IN5T3yqklWiQg-Kow",
      "pictureSource": "Agerpres",
      "relatedSearch": [
        {
          "title": "JO 2026 - Sărituri cu schiurile: Norvegianca Stroem, medaliată cu aur; românca Daniela Toth, pe locul 30",
          "snippet": "",
          "url": "https://agerpres.ro/sport-extern/2026/02/07/jo-2026---sarituri-cu-schiurile-norvegianca-stroem-medaliata-cu-aur-romanca-daniela-toth-pe-locul-30--1525943",
          "source": "Agerpres"
        },
        {
          "title": "Daniela Toth – povestea copilului care a învățat să zboare pe schiuri",
          "snippet": "",
          "url": "http://www.tvr.ro/daniela-toth-povestea-copilului-care-a-inva-at-sa-zboare-pe-schiuri_54163.html",
          "source": "TVR.RO"
        },
        {
          "title": "Jocurile Olimpice de iarnă 2026. Cine este Daniela Haralambie, cea mai săritoare fată din România",
          "snippet": "",
          "url": "https://www.libertatea.ro/sport/jocurile-olimpice-iarna-2026-cine-este-daniela-haralambie-saritoare-schiuri-5608324",
          "source": "Libertatea"
        }
      ],
      "link": "https://imtaqin.id/"
    }
  ]
}